src_mcp/__init__.py
src_mcp/__main__.py
src_mcp/server.py
src_mcp-0.1.0.dist-info/METADATA
src_mcp-0.1.0.dist-info/WHEEL
src_mcp-0.1.0.dist-info/entry_points.txt
src_mcp-0.1.0.dist-info/licenses/LICENSE
src_mcp-0.1.0.dist-info/RECORD
