Metadata-Version: 2.4
Name: src_mcp
Version: 0.1.0
Summary: A Model Context Protocol (MCP) time server with timezone support
Project-URL: Homepage, https://github.com/SRC/src_mcp
Project-URL: Repository, https://github.com/SRC/src_mcp
Project-URL: Issues, https://github.com/SRC/src_mcp/issues
Author-email: SRC <3484185597@qq.com>
License: MIT
License-File: LICENSE
Keywords: cherry-studio,mcp,model-context-protocol,time,timezone
Classifier: Development Status :: 3 - Alpha
Classifier: Intended Audience :: Developers
Classifier: License :: OSI Approved :: MIT License
Classifier: Programming Language :: Python :: 3
Classifier: Programming Language :: Python :: 3.10
Classifier: Programming Language :: Python :: 3.11
Classifier: Programming Language :: Python :: 3.12
Requires-Python: >=3.10
Requires-Dist: mcp>=1.0.0
Requires-Dist: pytz>=2024.1
Provides-Extra: dev
Requires-Dist: build>=1.0.0; extra == 'dev'
Requires-Dist: pytest-asyncio>=0.23.0; extra == 'dev'
Requires-Dist: pytest>=8.0.0; extra == 'dev'
Requires-Dist: twine>=5.0.0; extra == 'dev'
Requires-Dist: wheel>=0.42.0; extra == 'dev'
